README.md
setup.cfg
setup.py
yosaipy2/__init__.py
yosaipy2.egg-info/PKG-INFO
yosaipy2.egg-info/SOURCES.txt
yosaipy2.egg-info/dependency_links.txt
yosaipy2.egg-info/not-zip-safe
yosaipy2.egg-info/requires.txt
yosaipy2.egg-info/top_level.txt
yosaipy2/account_store/__init__.py
yosaipy2/account_store/account_store.py
yosaipy2/account_store/models.py
yosaipy2/core/__init__.py
yosaipy2/core/exceptions.py
yosaipy2/core/account/__init__.py
yosaipy2/core/account/abcs.py
yosaipy2/core/account/account.py
yosaipy2/core/authc/__init__.py
yosaipy2/core/authc/abcs.py
yosaipy2/core/authc/authc.py
yosaipy2/core/authc/authc_settings.py
yosaipy2/core/authc/credential.py
yosaipy2/core/authc/strategy.py
yosaipy2/core/authz/__init__.py
yosaipy2/core/authz/abcs.py
yosaipy2/core/authz/authz.py
yosaipy2/core/cache/__init__.py
yosaipy2/core/cache/abcs.py
yosaipy2/core/cache/backend.py
yosaipy2/core/cache/cache_handler.py
yosaipy2/core/cache/settings.py
yosaipy2/core/concurrency/__init__.py
yosaipy2/core/concurrency/concurrency.py
yosaipy2/core/conf/__init__.py
yosaipy2/core/conf/yosaisettings.py
yosaipy2/core/event/__init__.py
yosaipy2/core/event/abcs.py
yosaipy2/core/event/event.py
yosaipy2/core/event/event_bus.py
yosaipy2/core/logging/__init__.py
yosaipy2/core/logging/formatters.py
yosaipy2/core/logging/slogging.py
yosaipy2/core/mgt/__init__.py
yosaipy2/core/mgt/abcs.py
yosaipy2/core/mgt/mgt.py
yosaipy2/core/mgt/mgt_settings.py
yosaipy2/core/realm/__init__.py
yosaipy2/core/realm/abcs.py
yosaipy2/core/realm/realm.py
yosaipy2/core/serialize/__init__.py
yosaipy2/core/serialize/abcs.py
yosaipy2/core/serialize/manager.py
yosaipy2/core/serialize/serializer.py
yosaipy2/core/session/__init__.py
yosaipy2/core/session/abcs.py
yosaipy2/core/session/manager.py
yosaipy2/core/session/schema.py
yosaipy2/core/session/session.py
yosaipy2/core/session/session_settings.py
yosaipy2/core/session/session_store.py
yosaipy2/core/subject/__init__.py
yosaipy2/core/subject/abcs.py
yosaipy2/core/subject/identifier.py
yosaipy2/core/subject/schema.py
yosaipy2/core/subject/subject.py
yosaipy2/core/utils/__init__.py
yosaipy2/core/utils/utils.py
yosaipy2/registry/__init__.py
